simpleshark/__init__.py
simpleshark/config.ini
simpleshark/config.py
simpleshark/capture/__init__.py
simpleshark/capture/capture.py
simpleshark/packet/__init__.py
simpleshark/packet/common.py
simpleshark/packet/consts.py
simpleshark/packet/fields.py
simpleshark/packet/packet.py
simpleshark/packet/packet_summary.py
simpleshark/tshark/__init__.py
simpleshark/tshark/tshark.py
simpleshark/tshark/tshark_xml.py
simpleshark-0.0.13.dist-info/LICENSE
simpleshark-0.0.13.dist-info/METADATA
simpleshark-0.0.13.dist-info/WHEEL
simpleshark-0.0.13.dist-info/top_level.txt
simpleshark-0.0.13.dist-info/RECORD
