Metadata-Version: 2.1
Name: simpleshark
Version: 0.0.13
Summary: Python package to parse tshark/wireshark/tcpdump captured pcaps and return python objects.
Home-page: https://github.com/naveenraju23/simpleshark
Author: Naveen Raju
Author-email: naveen.raju23@gmail.com
Keywords: wireshark packets parsing pcap packets
Classifier: Programming Language :: Python :: 3
Classifier: Operating System :: OS Independent
Requires-Python: >=3.5
License-File: LICENSE
Requires-Dist: lxml
Requires-Dist: py
